splunk_downloader/__init__.py
splunk_downloader/__main__.py
splunk_downloader/constants.py
splunk_downloader-0.2.0.dist-info/METADATA
splunk_downloader-0.2.0.dist-info/WHEEL
splunk_downloader-0.2.0.dist-info/entry_points.txt
splunk_downloader-0.2.0.dist-info/RECORD
