Metadata-Version: 2.4
Name: splunk-downloader
Version: 0.2.0
Summary: Download your Splunk binaries with this quick tool.
Author-email: James Hodgkinson <james@terminaloutcomes.com>
License: MIT
Requires-Python: >=3.12
Requires-Dist: beautifulsoup4>=4.12.3
Requires-Dist: click>=8.1.7
Requires-Dist: loguru>=0.7.2
Requires-Dist: packaging>=24.1
Requires-Dist: pydantic>=2.9.1
Requires-Dist: requests>=2.32.3
